skytools/parsing.py
skytools/querybuilder.py
skytools/utf8.py
skytools/_cquoting.abi3.so
skytools/_chashtext.abi3.so
skytools/__init__.py
skytools/plpy_applyrow.py
skytools/adminscript.py
skytools/quoting.py
skytools/dbservice.py
skytools/hashtext.py
skytools/apipkg.py
skytools/config.py
skytools/tnetstrings.py
skytools/dbstruct.py
skytools/_cquoting.pyi
skytools/sqltools.py
skytools/basetypes.py
skytools/natsort.py
skytools/sockutil.py
skytools/_chashtext.pyi
skytools/gzlog.py
skytools/py.typed
skytools/skylog.py
skytools/_pyquoting.py
skytools/psycopgwrapper.py
skytools/checker.py
skytools/fileutil.py
skytools/timeutil.py
skytools/scripting.py
skytools/installer_config.py
skytools-3.9.2.dist-info/RECORD
skytools-3.9.2.dist-info/WHEEL
skytools-3.9.2.dist-info/AUTHORS
skytools-3.9.2.dist-info/METADATA
skytools-3.9.2.dist-info/top_level.txt
