Metadata-Version: 2.1
Name: skytools
Version: 3.9.2
Summary: Utilities for database scripts
Maintainer-email: Marko Kreen <markokr@gmail.com>
Project-URL: homepage, https://github.com/pgq/python-skytools
Project-URL: repository, https://github.com/pgq/python-skytools
Project-URL: changelog, https://github.com/pgq/python-skytools/blob/master/NEWS.rst
Keywords: database
Classifier: Development Status :: 5 - Production/Stable
Classifier: Environment :: Console
Classifier: Intended Audience :: Developers
Classifier: License :: OSI Approved :: ISC License (ISCL)
Classifier: Operating System :: MacOS :: MacOS X
Classifier: Operating System :: Microsoft :: Windows
Classifier: Operating System :: POSIX
Classifier: Programming Language :: Python :: 3
Classifier: Topic :: Database
Classifier: Topic :: Software Development :: Libraries :: Python Modules
Classifier: Topic :: Utilities
Requires-Python: >=3.7
License-File: AUTHORS
Provides-Extra: doc
Requires-Dist: sphinx ; extra == 'doc'
Provides-Extra: test
Requires-Dist: pytest ; extra == 'test'
Requires-Dist: pytest-cov ; extra == 'test'
Requires-Dist: coverage[toml] ; extra == 'test'
Requires-Dist: psycopg2-binary ; extra == 'test'
